LICENSE
README.md
setup.cfg
setup.py
Painless_SQLAlchemy.egg-info/PKG-INFO
Painless_SQLAlchemy.egg-info/SOURCES.txt
Painless_SQLAlchemy.egg-info/dependency_links.txt
Painless_SQLAlchemy.egg-info/not-zip-safe
Painless_SQLAlchemy.egg-info/requires.txt
Painless_SQLAlchemy.egg-info/top_level.txt
painless_sqlalchemy/__init__.py
painless_sqlalchemy/columns/AbstractGeometry.py
painless_sqlalchemy/columns/AbstractType.py
painless_sqlalchemy/columns/AreaType.py
painless_sqlalchemy/columns/CIText.py
painless_sqlalchemy/columns/HexColorType.py
painless_sqlalchemy/columns/LocationType.py
painless_sqlalchemy/columns/TimeType.py
painless_sqlalchemy/columns/TimeZoneType.py
painless_sqlalchemy/columns/__init__.py
painless_sqlalchemy/core/Model.py
painless_sqlalchemy/core/ModelAction.py
painless_sqlalchemy/core/ModelFilter.py
painless_sqlalchemy/core/ModelRaw.py
painless_sqlalchemy/core/ModelSerialization.py
painless_sqlalchemy/core/ModelValidation.py
painless_sqlalchemy/core/__init__.py
painless_sqlalchemy/elements/ColumnReference.py
painless_sqlalchemy/elements/MapColumn.py
painless_sqlalchemy/elements/__init__.py
painless_sqlalchemy/util/DictUtil.py
painless_sqlalchemy/util/LocationUtil.py
painless_sqlalchemy/util/TableUtil.py
painless_sqlalchemy/util/__init__.py
painless_sqlalchemy/util/testing/AbstractDatabaseTest.py
painless_sqlalchemy/util/testing/AbstractExtendedTest.py
painless_sqlalchemy/util/testing/DBIdMixin.py
painless_sqlalchemy/util/testing/DBTestUtilMixin.py