Metadata-Version: 2.1
Name: Painless-SQLAlchemy
Version: 1.0.3
Summary: Simplified filtering and serialization for SQLAlchemy
Home-page: https://github.com/GetintheLoop/painless-sqlalchemy
Author: Lukas Siemon
Author-email: painless@blackflux.com
Maintainer: Lukas Siemon
Maintainer-email: painless@blackflux.com
License: MIT
Keywords: SQLAlchemy,Serialization,Query,Simple,Abstraction,PostGis,Columns
Platform: any
Provides-Extra: postgis
License-File: LICENSE
